{"Id":0,"Title":"Guidelines for Successful Remote Work","Content":"In today\u0027s digitally advanced age, remote work has become more prevalent and increasingly more popular. While there are numerous benefits to working remotely, it also comes with its unique challenges. This article provides practical guidelines to help you navigate the remote work realm and boost productivity while maintaining a positive work-life balance.\n\n1. Establish a Dedicated Workspace: Having a separate space for work helps maintain the work-life balance. It also enables you to concentrate better and minimizes distractions.\n\n2. Maintain Regular Work Hours: While flexibility is one of the perks of remote work, maintaining a regular schedule can enhance your efficiency.\n\n3. Use Technology: Numerous tools and apps facilitate remote work. Leveraging these tools not only helps you manage your tasks but also enables easy collaboration with your team.\n\n4. Take Breaks: Regular breaks are essential to keep your mind fresh and maintain your productivity levels.\n\n5. Keep Communication Open: Regular communication with your team helps keep everyone in sync and fosters a team environment.\n\n6. Prioritize Tasks: Create a to-do list and prioritize tasks based on their urgency and importance. This helps you manage your workload and increases your productivity.\n\n7. Stay Healthy: Prioritize your health by taking breaks, eating well, and exercising. Sitting for long hours can take a toll on your health, so make sure to move around and stretch regularly.\n\nImplementing these guidelines can significantly enhance your remote work experience. Remember, remote work requires a certain level of discipline and dedication, but with the right strategies in place, you can enjoy the abundant benefits it offers.","Author":"Jennifer Rowland","CreatedAt":"0001-01-01T00:00:00"}